esprimo/esprimo_yhq.py
esprimo/primoshasta_yhq.py
esprimo-1.0.dist-info/LICENSE.txt
esprimo-1.0.dist-info/METADATA
esprimo-1.0.dist-info/WHEEL
esprimo-1.0.dist-info/top_level.txt
esprimo-1.0.dist-info/RECORD
